[{"@odata.etag":"","ItemInternalId":"ea0dfb75-9f62-4f95-8121-10e42fae4dec","id":"t8f3k2a1x01","title":"Cotizar material para pedido de julio","desc":"Pedir 3 cotizaciones a proveedores habituales.","resp":"María","due":"46221","prio":"alta","meet":"Reunión de producción","meetdate":"46218","status":"pendiente","created_at":"2026-07-16T09:00:00","updated_at":"2026-07-16T09:00:00","updated_by":"jleonm506@gmail.com","sync_status":"sincronizado","deleted":"no"},{"@odata.etag":"","ItemInternalId":"d96041af-713c-4576-be56-ee2347642f57","id":"t8f3k2a1x02","title":"Actualizar checklist de mantenimiento","desc":"","resp":"Carlos","due":"46224","prio":"media","meet":"Reunión de producción","meetdate":"46218","status":"proceso","created_at":"2026-07-16T09:00:00","updated_at":"2026-07-16T09:00:00","updated_by":"jleonm506@gmail.com","sync_status":"sincronizado","deleted":"no"},{"@odata.etag":"","ItemInternalId":"8badb9a7-2b18-4853-95a4-c1845297f14b","id":"t8f3k2a1x03","title":"Enviar reporte de calidad semanal","desc":"Compartir al grupo antes del viernes.","resp":"Ana","due":"46218","prio":"media","meet":"Seguimiento semanal","meetdate":"46216","status":"proceso","created_at":"2026-07-16T09:00:00","updated_at":"2026-07-16T09:00:00","updated_by":"Jose","sync_status":"sincronizado","deleted":"no"},{"@odata.etag":"","ItemInternalId":"c2b1da31-b990-4d54-bc39-19512c1ca0e2","id":"t8f3k2a1x04","title":"Confirmar entrega con transportista","desc":"","resp":"José","due":"46219","prio":"alta","meet":"Seguimiento semanal","meetdate":"46216","status":"pendiente","created_at":"2026-07-16T09:00:00","updated_at":"2026-07-16T09:00:00","updated_by":"Jose","sync_status":"sincronizado","deleted":"no"},{"@odata.etag":"","ItemInternalId":"af5c218a-305c-4fd0-9c5d-f50d84a378b2","id":"t8f3k2a1x05","title":"Prueba","desc":"Prueba","resp":"Alexander","due":"46219","prio":"alta","meet":"Reunión de producción","meetdate":"46219","status":"proceso","created_at":"2026-07-16T09:00:00","updated_at":"2026-07-16T09:00:00","updated_by":"Jose","sync_status":"sincronizado","deleted":"si"},{"@odata.etag":"","ItemInternalId":"749b2965-6e14-4ddc-a587-31c165d76236","id":"t6qgk82yh0b","title":"Prueba 2","desc":"Prueba ALEX","resp":"José","due":"46220","prio":"alta","meet":"Reunión de producción","meetdate":"46220","status":"proceso","created_at":"","updated_at":"","updated_by":"Jose","sync_status":"","deleted":"si"},{"@odata.etag":"","ItemInternalId":"dd44f09c-bfaa-4cc2-9aed-90c395222600","id":"tkygxlsd2kj","title":"Prueba","desc":"preuba 3","resp":"Ana","due":"46220","prio":"alta","meet":"","meetdate":"46220","status":"pendiente","created_at":"","updated_at":"","updated_by":"Jose","sync_status":"","deleted":"no"}]