[{"@odata.etag":"","ItemInternalId":"2ce9e82e-9a19-4298-9774-e0b0b2760bf0","id":"txw362uzm4c","title":"Cierres WO","desc":"Diseñar proceso para cierres ágiles de WO.","resp":"Marco","due":"46225","prio":"alta","meet":"Seguimiento de tareas","meetdate":"","status":"pendiente","created_at":"","updated_at":"","updated_by":"JFS","sync_status":"","deleted":"si","Comentario":""},{"@odata.etag":"","ItemInternalId":"235beb92-7111-446b-8e89-af39fd596085","id":"tt4t243g56x","title":"Capacitación nuevo ingreso Digitador.","desc":"Capacitar y acompañar a nuevo ingreso digitador de almacén.","resp":"Eva","due":"46241","prio":"alta","meet":"Seguimiento de tareas","meetdate":"","status":"pendiente","created_at":"","updated_at":"","updated_by":"JFS","sync_status":"","deleted":"no","Comentario":""},{"@odata.etag":"","ItemInternalId":"782a043f-95c9-4e8d-87e3-43ed76cd0a5c","id":"t0ytzl4qeei","title":"Capacitación operador Almacén.","desc":"Capacitar al nuevo operador de almacén (Edilson)","resp":"Erick","due":"46237","prio":"alta","meet":"Seguimiento de tareas","meetdate":"","status":"pendiente","created_at":"","updated_at":"","updated_by":"JFS","sync_status":"","deleted":"no","Comentario":""},{"@odata.etag":"","ItemInternalId":"45683ee5-de70-4a75-b1d2-b9e558d751b3","id":"t2ia39379rz","title":"Implementación 6S Almacén.","desc":"Capacitar e implementar la metodología de 6S en almacén.","resp":"Eva","due":"46249","prio":"baja","meet":"Administración diaria","meetdate":"46234","status":"pendiente","created_at":"","updated_at":"","updated_by":"JFS","sync_status":"","deleted":"no","Comentario":""},{"@odata.etag":"","ItemInternalId":"df9182f5-b14c-4285-ba45-fd505a76708c","id":"tlm7ebzakdc","title":"Implementación 6S Almacén.","desc":"Capacitar e implementar la metodología de 6S en Almacén","resp":"Erick","due":"46234","prio":"baja","meet":"Administración diaria","meetdate":"46249","status":"pendiente","created_at":"","updated_at":"","updated_by":"JFS","sync_status":"","deleted":"si","Comentario":""},{"@odata.etag":"","ItemInternalId":"07be3f04-58e0-437d-9cf4-c31ce1536934","id":"tlm7ebzakdc","title":"Implementación 6S Almacén.","desc":"Capacitar e implementar la metodología de 6S en Almacén","resp":"Erick","due":"46219","prio":"baja","meet":"Administración diaria","meetdate":"46249","status":"pendiente","created_at":"","updated_at":"","updated_by":"JFS","sync_status":"","deleted":"no","Comentario":""},{"@odata.etag":"","ItemInternalId":"7bfe96af-496d-4fc0-ad34-5bc7c87dc769","id":"t0iqnghmk9t","title":"Implementación 6S Almacén.","desc":"Capacitar e implementar la metodología de 6 S en almacén.","resp":"Wallace","due":"46234","prio":"baja","meet":"Administración diaria","meetdate":"46219","status":"pendiente","created_at":"","updated_at":"","updated_by":"JFS","sync_status":"","deleted":"no","Comentario":""},{"@odata.etag":"","ItemInternalId":"dc395fd3-7ec3-49d7-be5b-9537f7a39519","id":"t1gory2fsb4","title":"Definir horarios Supervisores.","desc":"Definir rotacional de supervisores mes de agosto.","resp":"Marco","due":"46232","prio":"baja","meet":"Seguimiento de tareas","meetdate":"","status":"proceso","created_at":"","updated_at":"","updated_by":"JFS","sync_status":"","deleted":"no","Comentario":""},{"@odata.etag":"","ItemInternalId":"282403c9-2b91-4b5b-bf59-01474b0b15d0","id":"tg54vc76xmo","title":"Cierre herramienta ICU.","desc":"cierre conciliación herramienta DUAS ICU.","resp":"Marco","due":"46220","prio":"alta","meet":"Seguimiento de tareas","meetdate":"46217","status":"proceso","created_at":"","updated_at":"","updated_by":"JFS","sync_status":"","deleted":"no","Comentario":""},{"@odata.etag":"","ItemInternalId":"e8281a3f-096f-4104-972c-5b061d9a2de9","id":"ttfnpmr0ziu","title":"Contratación digitador.","desc":"Contratación de nuevo personal","resp":"Marco","due":"46220","prio":"alta","meet":"Seguimiento de tareas","meetdate":"","status":"proceso","created_at":"","updated_at":"","updated_by":"JFS","sync_status":"","deleted":"no","Comentario":""},{"@odata.etag":"","ItemInternalId":"2fff0052-bf05-4973-92f1-e1ba693ac81f","id":"tjkm0p3i38w","title":"Re implementación de muelles empaque.","desc":"Diseñar, marcar e implementar muelles de empaque.","resp":"Wallace","due":"46234","prio":"media","meet":"Seguimiento de tareas","meetdate":"","status":"proceso","created_at":"","updated_at":"","updated_by":"JFS","sync_status":"","deleted":"no","Comentario":""},{"@odata.etag":"","ItemInternalId":"96e64c25-053f-449a-8ba2-a0eb221df4bc","id":"tfuixmd4qoc","title":"Capacitación profunda en WO Resineros.","desc":"Capacitación profunda a resineros en actividades de WO.","resp":"Wallace","due":"46232","prio":"media","meet":"Seguimiento de tareas","meetdate":"","status":"proceso","created_at":"","updated_at":"","updated_by":"JFS","sync_status":"","deleted":"no","Comentario":""},{"@odata.etag":"","ItemInternalId":"45a46dec-67b5-49cb-b3f9-f6958779c338","id":"txw362uzm4c","title":"Cierres WO.","desc":"Diseñar proceso para cierres ágiles de WO.","resp":"Marco","due":"46225","prio":"alta","meet":"Seguimiento de tareas","meetdate":"","status":"pendiente","created_at":"","updated_at":"","updated_by":"JFS","sync_status":"","deleted":"no","Comentario":""},{"@odata.etag":"","ItemInternalId":"7ad6d779-cbd0-4d88-9477-1eae4988c020","id":"th7f7og31uo","title":"Cambio en horario de molineros","desc":"Re acomodar los turnos de los molineros para dar soporte a ensamble automatizado.","resp":"Wallace","due":"46220","prio":"alta","meet":"Seguimiento de tareas","meetdate":"","status":"finalizada","created_at":"","updated_at":"","updated_by":"Jose","sync_status":"","deleted":"no","Comentario":""},{"@odata.etag":"","ItemInternalId":"4f26dc9f-37dc-4293-ba2b-17225c87e37d","id":"tuz5fxhpzqp","title":"Prueba Alex","desc":"Test","resp":"Alexander","due":"46225","prio":"alta","meet":"Reunión de producción","meetdate":"46225","status":"proceso","created_at":"","updated_at":"","updated_by":"ALM","sync_status":"","deleted":"si","Comentario":"Prueba para validación de tareas"},{"@odata.etag":"","ItemInternalId":"251aac18-7313-461e-a13e-04a7db60f886","id":"tuz5fxhpzqp","title":"Prueba Alex","desc":"Test","resp":"Alexander","due":"46225","prio":"alta","meet":"Reunión de producción","meetdate":"46225","status":"proceso","created_at":"","updated_at":"","updated_by":"Jose","sync_status":"","deleted":"si","Comentario":"Prueba para validación de tareas"},{"@odata.etag":"","ItemInternalId":"048987d7-77c6-4208-957e-77b0e2a3dc4e","id":"toee8ocyk8l","title":"Cotizar bolsa para el 82026 de Moog","desc":"Cotizar el incremento de la bolsa 9 al hacer el cambio por la anterior.","resp":"Jose","due":"46230","prio":"alta","meet":"Reunión con cliente","meetdate":"","status":"pendiente","created_at":"","updated_at":"","updated_by":"JFS","sync_status":"","deleted":"no","Comentario":"Revisar con Diego el cambio."}]