[{"@odata.etag":"","ItemInternalId":"b9a1a275-189d-4c00-9359-1cc1bcfa59b5","id":"txw362uzm4c","title":"Cierres WO","desc":"Diseñar proceso para cierres ágiles de WO.","resp":"Marco","due":"46225","prio":"alta","meet":"Seguimiento de tareas","meetdate":"","status":"pendiente","created_at":"","updated_at":"","updated_by":"JFS","sync_status":"","deleted":"si","Comentario":""},{"@odata.etag":"","ItemInternalId":"982ffce1-f395-47db-b776-1712c3a49050","id":"tt4t243g56x","title":"Capacitación nuevo ingreso Digitador.","desc":"Capacitar y acompañar a nuevo ingreso digitador de almacén.","resp":"Eva","due":"46241","prio":"alta","meet":"Seguimiento de tareas","meetdate":"","status":"pendiente","created_at":"","updated_at":"","updated_by":"JFS","sync_status":"","deleted":"no","Comentario":""},{"@odata.etag":"","ItemInternalId":"5411eeba-1ede-4de8-877a-f815e2b3f407","id":"t0ytzl4qeei","title":"Capacitación operador Almacén.","desc":"Capacitar al nuevo operador de almacén (Edilson)","resp":"Erick","due":"46237","prio":"alta","meet":"Seguimiento de tareas","meetdate":"","status":"pendiente","created_at":"","updated_at":"","updated_by":"JFS","sync_status":"","deleted":"no","Comentario":""},{"@odata.etag":"","ItemInternalId":"952af2e1-c483-4467-91ae-10c60e2f3914","id":"t2ia39379rz","title":"Implementación 6S Almacén.","desc":"Capacitar e implementar la metodología de 6S en almacén.","resp":"Eva","due":"46249","prio":"baja","meet":"Administración diaria","meetdate":"46234","status":"pendiente","created_at":"","updated_at":"","updated_by":"JFS","sync_status":"","deleted":"no","Comentario":""},{"@odata.etag":"","ItemInternalId":"cbd65f32-9db6-4330-bc6e-92261cb97797","id":"tlm7ebzakdc","title":"Implementación 6S Almacén.","desc":"Capacitar e implementar la metodología de 6S en Almacén","resp":"Erick","due":"46234","prio":"baja","meet":"Administración diaria","meetdate":"46249","status":"pendiente","created_at":"","updated_at":"","updated_by":"JFS","sync_status":"","deleted":"si","Comentario":""},{"@odata.etag":"","ItemInternalId":"e1e58cea-a228-4683-af96-6d77ee54dba0","id":"tlm7ebzakdc","title":"Implementación 6S Almacén.","desc":"Capacitar e implementar la metodología de 6S en Almacén","resp":"Erick","due":"46219","prio":"baja","meet":"Administración diaria","meetdate":"46249","status":"pendiente","created_at":"","updated_at":"","updated_by":"JFS","sync_status":"","deleted":"no","Comentario":""},{"@odata.etag":"","ItemInternalId":"e2ddb1d0-6f7e-464b-81ef-4e277c397b9e","id":"t0iqnghmk9t","title":"Implementación 6S Almacén.","desc":"Capacitar e implementar la metodología de 6 S en almacén.","resp":"Wallace","due":"46234","prio":"baja","meet":"Administración diaria","meetdate":"46219","status":"pendiente","created_at":"","updated_at":"","updated_by":"JFS","sync_status":"","deleted":"no","Comentario":""},{"@odata.etag":"","ItemInternalId":"67a6cb01-49e5-48d2-a566-05a995defebe","id":"t1gory2fsb4","title":"Definir horarios Supervisores.","desc":"Definir rotacional de supervisores mes de agosto.","resp":"Marco","due":"46232","prio":"baja","meet":"Seguimiento de tareas","meetdate":"","status":"proceso","created_at":"","updated_at":"","updated_by":"JFS","sync_status":"","deleted":"no","Comentario":""},{"@odata.etag":"","ItemInternalId":"ff32aad3-db69-42aa-9a15-0df1fcfd6e45","id":"tg54vc76xmo","title":"Cierre herramienta ICU.","desc":"cierre conciliación herramienta DUAS ICU.","resp":"Marco","due":"46220","prio":"alta","meet":"Seguimiento de tareas","meetdate":"46217","status":"proceso","created_at":"","updated_at":"","updated_by":"JFS","sync_status":"","deleted":"no","Comentario":""},{"@odata.etag":"","ItemInternalId":"7cba1698-66f9-47e9-8398-1b2724c37ec5","id":"ttfnpmr0ziu","title":"Contratación digitador.","desc":"Contratación de nuevo personal","resp":"Marco","due":"46220","prio":"alta","meet":"Seguimiento de tareas","meetdate":"","status":"proceso","created_at":"","updated_at":"","updated_by":"JFS","sync_status":"","deleted":"no","Comentario":""},{"@odata.etag":"","ItemInternalId":"05adcc99-f5a5-4304-8592-b05d667edbcd","id":"tjkm0p3i38w","title":"Re implementación de muelles empaque.","desc":"Diseñar, marcar e implementar muelles de empaque.","resp":"Wallace","due":"46234","prio":"media","meet":"Seguimiento de tareas","meetdate":"","status":"proceso","created_at":"","updated_at":"","updated_by":"JFS","sync_status":"","deleted":"no","Comentario":""},{"@odata.etag":"","ItemInternalId":"a47b0bc6-f689-44ba-9d08-f692d594b2dc","id":"tfuixmd4qoc","title":"Capacitación profunda en WO Resineros.","desc":"Capacitación profunda a resineros en actividades de WO.","resp":"Wallace","due":"46232","prio":"media","meet":"Seguimiento de tareas","meetdate":"","status":"proceso","created_at":"","updated_at":"","updated_by":"JFS","sync_status":"","deleted":"no","Comentario":""},{"@odata.etag":"","ItemInternalId":"41bacef7-a774-48bb-bac6-5cdc766667b0","id":"txw362uzm4c","title":"Cierres WO.","desc":"Diseñar proceso para cierres ágiles de WO.","resp":"Marco","due":"46225","prio":"alta","meet":"Seguimiento de tareas","meetdate":"","status":"pendiente","created_at":"","updated_at":"","updated_by":"JFS","sync_status":"","deleted":"no","Comentario":""},{"@odata.etag":"","ItemInternalId":"3a6addf2-be00-474b-b65c-54ffeb72cd9b","id":"th7f7og31uo","title":"Cambio en horario de molineros","desc":"Re acomodar los turnos de los molineros para dar soporte a ensamble automatizado.","resp":"Wallace","due":"46220","prio":"alta","meet":"Seguimiento de tareas","meetdate":"","status":"finalizada","created_at":"","updated_at":"","updated_by":"Jose","sync_status":"","deleted":"no","Comentario":""},{"@odata.etag":"","ItemInternalId":"4793cfc3-5bc2-4b70-8927-99b53dbb3912","id":"tuz5fxhpzqp","title":"Prueba Alex","desc":"Test","resp":"Alexander","due":"46225","prio":"alta","meet":"Reunión de producción","meetdate":"46225","status":"proceso","created_at":"","updated_at":"","updated_by":"Jose","sync_status":"","deleted":"no","Comentario":"Prueba para validación de tareas"},{"@odata.etag":"","ItemInternalId":"1af6c296-182a-4948-b09c-4b4243bd58d1","id":"tuz5fxhpzqp","title":"Prueba Alex","desc":"Test","resp":"Alexander","due":"46225","prio":"alta","meet":"Reunión de producción","meetdate":"46225","status":"proceso","created_at":"","updated_at":"","updated_by":"Jose","sync_status":"","deleted":"si","Comentario":"Prueba para validación de tareas"}]