[{"@odata.etag":"","ItemInternalId":"ec67db46-6aa7-4fcc-b823-570d1a22c1c0","id":"txw362uzm4c","title":"Cierres WO","desc":"Diseñar proceso para cierres ágiles de WO.","resp":"Marco","due":"46225","prio":"alta","meet":"Seguimiento de tareas","meetdate":"","status":"pendiente","created_at":"","updated_at":"","updated_by":"JFS","sync_status":"","deleted":"si"},{"@odata.etag":"","ItemInternalId":"a128f257-f349-4ead-9077-eee9d4b19d5a","id":"tt4t243g56x","title":"Capacitación nuevo ingreso Digitador.","desc":"Capacitar y acompañar a nuevo ingreso digitador de almacén.","resp":"Eva","due":"46241","prio":"alta","meet":"Seguimiento de tareas","meetdate":"","status":"pendiente","created_at":"","updated_at":"","updated_by":"JFS","sync_status":"","deleted":"no"},{"@odata.etag":"","ItemInternalId":"a245d9f1-3246-4238-8514-eceac33f8ff0","id":"t0ytzl4qeei","title":"Capacitación operador Almacén.","desc":"Capacitar al nuevo operador de almacén (Edilson)","resp":"Erick","due":"46237","prio":"alta","meet":"Seguimiento de tareas","meetdate":"","status":"pendiente","created_at":"","updated_at":"","updated_by":"JFS","sync_status":"","deleted":"no"},{"@odata.etag":"","ItemInternalId":"a9b11bc4-f3c9-4b8d-9146-cde3dea2fb82","id":"t2ia39379rz","title":"Implementación 6S Almacén.","desc":"Capacitar e implementar la metodología de 6S en almacén.","resp":"Eva","due":"46249","prio":"baja","meet":"Administración diaria","meetdate":"46234","status":"pendiente","created_at":"","updated_at":"","updated_by":"JFS","sync_status":"","deleted":"no"},{"@odata.etag":"","ItemInternalId":"161d8c99-9d3c-4309-b716-8accf11e43b6","id":"tlm7ebzakdc","title":"Implementación 6S Almacén.","desc":"Capacitar e implementar la metodología de 6S en Almacén","resp":"Erick","due":"46234","prio":"baja","meet":"Administración diaria","meetdate":"46249","status":"pendiente","created_at":"","updated_at":"","updated_by":"JFS","sync_status":"","deleted":"si"},{"@odata.etag":"","ItemInternalId":"aa9ab02d-da49-4219-93f7-320a3ea23a4f","id":"tlm7ebzakdc","title":"Implementación 6S Almacén.","desc":"Capacitar e implementar la metodología de 6S en Almacén","resp":"Erick","due":"46219","prio":"baja","meet":"Administración diaria","meetdate":"46249","status":"pendiente","created_at":"","updated_at":"","updated_by":"JFS","sync_status":"","deleted":"no"},{"@odata.etag":"","ItemInternalId":"43cb8d7b-0ff5-40f5-b240-89d6bebe3ab0","id":"t0iqnghmk9t","title":"Implementación 6S Almacén.","desc":"Capacitar e implementar la metodología de 6 S en almacén.","resp":"Wallace","due":"46234","prio":"baja","meet":"Administración diaria","meetdate":"46219","status":"pendiente","created_at":"","updated_at":"","updated_by":"JFS","sync_status":"","deleted":"no"},{"@odata.etag":"","ItemInternalId":"2f229f4c-5776-4619-9c78-c0c40ea274fe","id":"t1gory2fsb4","title":"Definir horarios Supervisores.","desc":"Definir rotacional de supervisores mes de agosto.","resp":"Marco","due":"46232","prio":"baja","meet":"Seguimiento de tareas","meetdate":"","status":"proceso","created_at":"","updated_at":"","updated_by":"JFS","sync_status":"","deleted":"no"},{"@odata.etag":"","ItemInternalId":"5596487a-f22a-41ab-b124-7c61464c02e4","id":"tg54vc76xmo","title":"Cierre herramienta ICU.","desc":"cierre conciliación herramienta DUAS ICU.","resp":"Marco","due":"46220","prio":"alta","meet":"Seguimiento de tareas","meetdate":"46217","status":"proceso","created_at":"","updated_at":"","updated_by":"JFS","sync_status":"","deleted":"no"},{"@odata.etag":"","ItemInternalId":"a1d74fcc-de86-472f-95bb-d34b13645e7a","id":"ttfnpmr0ziu","title":"Contratación digitador.","desc":"Contratación de nuevo personal","resp":"Marco","due":"46220","prio":"alta","meet":"Seguimiento de tareas","meetdate":"","status":"proceso","created_at":"","updated_at":"","updated_by":"JFS","sync_status":"","deleted":"no"},{"@odata.etag":"","ItemInternalId":"7d0ab13b-6d44-4d16-8985-6a527971e072","id":"tjkm0p3i38w","title":"Re implementación de muelles empaque.","desc":"Diseñar, marcar e implementar muelles de empaque.","resp":"Wallace","due":"46234","prio":"media","meet":"Seguimiento de tareas","meetdate":"","status":"proceso","created_at":"","updated_at":"","updated_by":"JFS","sync_status":"","deleted":"no"},{"@odata.etag":"","ItemInternalId":"db0f9c85-63ec-4838-94c0-27b2c094e025","id":"tfuixmd4qoc","title":"Capacitación profunda en WO Resineros.","desc":"Capacitación profunda a resineros en actividades de WO.","resp":"Wallace","due":"46232","prio":"media","meet":"Seguimiento de tareas","meetdate":"","status":"proceso","created_at":"","updated_at":"","updated_by":"JFS","sync_status":"","deleted":"no"},{"@odata.etag":"","ItemInternalId":"d4176dee-2a25-44fa-a032-328d5976c733","id":"txw362uzm4c","title":"Cierres WO.","desc":"Diseñar proceso para cierres ágiles de WO.","resp":"Marco","due":"46225","prio":"alta","meet":"Seguimiento de tareas","meetdate":"","status":"pendiente","created_at":"","updated_at":"","updated_by":"JFS","sync_status":"","deleted":"no"},{"@odata.etag":"","ItemInternalId":"6859c2a0-1b17-4a81-a0f4-a5e8dba11d71","id":"th7f7og31uo","title":"Cambio en horario de molineros","desc":"Re acomodar los turnos de los molineros para dar soporte a ensamble automatizado.","resp":"Wallace","due":"46220","prio":"alta","meet":"Seguimiento de tareas","meetdate":"","status":"proceso","created_at":"","updated_at":"","updated_by":"JFS","sync_status":"","deleted":"no"}]