[{"@odata.etag":"","ItemInternalId":"ec6e19bf-f6e6-4735-b2a9-fb7564002fec","id":"txw362uzm4c","title":"Cierres WO","desc":"Diseñar proceso para cierres ágiles de WO.","resp":"Marco","due":"46225","prio":"alta","meet":"Seguimiento de tareas","meetdate":"","status":"pendiente","created_at":"","updated_at":"","updated_by":"JFS","sync_status":"","deleted":"si"},{"@odata.etag":"","ItemInternalId":"2cab28cb-9e08-4012-8a3c-069e66535ab5","id":"tt4t243g56x","title":"Capacitación nuevo ingreso Digitador.","desc":"Capacitar y acompañar a nuevo ingreso digitador de almacén.","resp":"Eva","due":"46241","prio":"alta","meet":"Seguimiento de tareas","meetdate":"","status":"pendiente","created_at":"","updated_at":"","updated_by":"JFS","sync_status":"","deleted":"no"},{"@odata.etag":"","ItemInternalId":"7f17f7c7-bbca-484e-9e1d-b4c09530cd52","id":"t0ytzl4qeei","title":"Capacitación operador Almacén.","desc":"Capacitar al nuevo operador de almacén (Edilson)","resp":"Erick","due":"46237","prio":"alta","meet":"Seguimiento de tareas","meetdate":"","status":"pendiente","created_at":"","updated_at":"","updated_by":"JFS","sync_status":"","deleted":"no"},{"@odata.etag":"","ItemInternalId":"83ab4458-a90a-483e-b672-28694e69528d","id":"t2ia39379rz","title":"Implementación 6S Almacén.","desc":"Capacitar e implementar la metodología de 6S en almacén.","resp":"Eva","due":"46249","prio":"baja","meet":"Administración diaria","meetdate":"46234","status":"pendiente","created_at":"","updated_at":"","updated_by":"JFS","sync_status":"","deleted":"no"},{"@odata.etag":"","ItemInternalId":"87b9dc96-0bd7-4ee3-a3bd-0e418705f4ef","id":"tlm7ebzakdc","title":"Implementación 6S Almacén.","desc":"Capacitar e implementar la metodología de 6S en Almacén","resp":"Erick","due":"46234","prio":"baja","meet":"Administración diaria","meetdate":"46249","status":"pendiente","created_at":"","updated_at":"","updated_by":"JFS","sync_status":"","deleted":"si"},{"@odata.etag":"","ItemInternalId":"18995c61-517f-43aa-86e8-a9c733db17fc","id":"tlm7ebzakdc","title":"Implementación 6S Almacén.","desc":"Capacitar e implementar la metodología de 6S en Almacén","resp":"Erick","due":"46219","prio":"baja","meet":"Administración diaria","meetdate":"46249","status":"pendiente","created_at":"","updated_at":"","updated_by":"JFS","sync_status":"","deleted":"no"},{"@odata.etag":"","ItemInternalId":"75b535ba-87a0-4ced-8766-7818df7846c6","id":"t0iqnghmk9t","title":"Implementación 6S Almacén.","desc":"Capacitar e implementar la metodología de 6 S en almacén.","resp":"Wallace","due":"46234","prio":"baja","meet":"Administración diaria","meetdate":"46219","status":"pendiente","created_at":"","updated_at":"","updated_by":"JFS","sync_status":"","deleted":"no"},{"@odata.etag":"","ItemInternalId":"5e33d47b-95d0-4564-96b8-8f49c0ec1d16","id":"t1gory2fsb4","title":"Definir horarios Supervisores.","desc":"Definir rotacional de supervisores mes de agosto.","resp":"Marco","due":"46232","prio":"baja","meet":"Seguimiento de tareas","meetdate":"","status":"proceso","created_at":"","updated_at":"","updated_by":"JFS","sync_status":"","deleted":"no"},{"@odata.etag":"","ItemInternalId":"2ea50dbe-d2d2-4fb1-99bc-9f16c2ee778c","id":"tg54vc76xmo","title":"Cierre herramienta ICU.","desc":"cierre conciliación herramienta DUAS ICU.","resp":"Marco","due":"46220","prio":"alta","meet":"Seguimiento de tareas","meetdate":"46217","status":"proceso","created_at":"","updated_at":"","updated_by":"JFS","sync_status":"","deleted":"no"},{"@odata.etag":"","ItemInternalId":"cbf1ab05-0ad9-47bf-8b5b-4a9b25d322ea","id":"ttfnpmr0ziu","title":"Contratación digitador.","desc":"Contratación de nuevo personal","resp":"Marco","due":"46220","prio":"alta","meet":"Seguimiento de tareas","meetdate":"","status":"proceso","created_at":"","updated_at":"","updated_by":"JFS","sync_status":"","deleted":"no"},{"@odata.etag":"","ItemInternalId":"c3e9586a-12e5-4992-b146-b06f27122ac1","id":"tjkm0p3i38w","title":"Re implementación de muelles empaque.","desc":"Diseñar, marcar e implementar muelles de empaque.","resp":"Wallace","due":"46234","prio":"media","meet":"Seguimiento de tareas","meetdate":"","status":"proceso","created_at":"","updated_at":"","updated_by":"JFS","sync_status":"","deleted":"no"},{"@odata.etag":"","ItemInternalId":"956b1b27-3668-4486-a41a-4b5d67c4606a","id":"tfuixmd4qoc","title":"Capacitación profunda en WO Resineros.","desc":"Capacitación profunda a resineros en actividades de WO.","resp":"Wallace","due":"46232","prio":"media","meet":"Seguimiento de tareas","meetdate":"","status":"proceso","created_at":"","updated_at":"","updated_by":"JFS","sync_status":"","deleted":"no"},{"@odata.etag":"","ItemInternalId":"ee03ab31-5e80-474b-b1de-eac0d4f75752","id":"txw362uzm4c","title":"Cierres WO.","desc":"Diseñar proceso para cierres ágiles de WO.","resp":"Marco","due":"46225","prio":"alta","meet":"Seguimiento de tareas","meetdate":"","status":"pendiente","created_at":"","updated_at":"","updated_by":"JFS","sync_status":"","deleted":"no"},{"@odata.etag":"","ItemInternalId":"887c5793-4d8c-4056-9eb7-87c05308ed0e","id":"th7f7og31uo","title":"Cambio en horario de molineros","desc":"Re acomodar los turnos de los molineros para dar soporte a ensamble automatizado.","resp":"Wallace","due":"46220","prio":"alta","meet":"Seguimiento de tareas","meetdate":"","status":"proceso","created_at":"","updated_at":"","updated_by":"JFS","sync_status":"","deleted":"no"}]