[{"@odata.etag":"","ItemInternalId":"8267a3e9-cd0e-4bbe-84c6-dacdc236983c","id":"txw362uzm4c","title":"Cierres WO","desc":"Diseñar proceso para cierres ágiles de WO.","resp":"Marco","due":"46225","prio":"alta","meet":"Seguimiento de tareas","meetdate":"","status":"pendiente","created_at":"","updated_at":"","updated_by":"JFS","sync_status":"","deleted":"si"},{"@odata.etag":"","ItemInternalId":"d07503fc-0cb2-4a12-b65d-dc6f220e57f6","id":"tt4t243g56x","title":"Capacitación nuevo ingreso Digitador.","desc":"Capacitar y acompañar a nuevo ingreso digitador de almacén.","resp":"Eva","due":"46241","prio":"alta","meet":"Seguimiento de tareas","meetdate":"","status":"pendiente","created_at":"","updated_at":"","updated_by":"JFS","sync_status":"","deleted":"no"},{"@odata.etag":"","ItemInternalId":"49fdaec5-7268-4984-8fa6-3cc345d81d9d","id":"t0ytzl4qeei","title":"Capacitación operador Almacén.","desc":"Capacitar al nuevo operador de almacén (Edilson)","resp":"Erick","due":"46237","prio":"alta","meet":"Seguimiento de tareas","meetdate":"","status":"pendiente","created_at":"","updated_at":"","updated_by":"JFS","sync_status":"","deleted":"no"},{"@odata.etag":"","ItemInternalId":"858705be-5fe8-4d42-9a31-b605638f3511","id":"t2ia39379rz","title":"Implementación 6S Almacén.","desc":"Capacitar e implementar la metodología de 6S en almacén.","resp":"Eva","due":"46249","prio":"baja","meet":"Administración diaria","meetdate":"46234","status":"pendiente","created_at":"","updated_at":"","updated_by":"JFS","sync_status":"","deleted":"no"},{"@odata.etag":"","ItemInternalId":"4ab3f529-6443-47dd-8765-ffc1b8608477","id":"tlm7ebzakdc","title":"Implementación 6S Almacén.","desc":"Capacitar e implementar la metodología de 6S en Almacén","resp":"Erick","due":"46234","prio":"baja","meet":"Administración diaria","meetdate":"46249","status":"pendiente","created_at":"","updated_at":"","updated_by":"JFS","sync_status":"","deleted":"si"},{"@odata.etag":"","ItemInternalId":"bd1c8a1e-fc91-4201-bf62-89893100acc9","id":"tlm7ebzakdc","title":"Implementación 6S Almacén.","desc":"Capacitar e implementar la metodología de 6S en Almacén","resp":"Erick","due":"46219","prio":"baja","meet":"Administración diaria","meetdate":"46249","status":"pendiente","created_at":"","updated_at":"","updated_by":"JFS","sync_status":"","deleted":"no"},{"@odata.etag":"","ItemInternalId":"4fd0c1e2-f0d5-404d-b4a7-71778c57cd13","id":"t0iqnghmk9t","title":"Implementación 6S Almacén.","desc":"Capacitar e implementar la metodología de 6 S en almacén.","resp":"Wallace","due":"46234","prio":"baja","meet":"Administración diaria","meetdate":"46219","status":"pendiente","created_at":"","updated_at":"","updated_by":"JFS","sync_status":"","deleted":"no"},{"@odata.etag":"","ItemInternalId":"b15a1646-ff7f-4455-8233-96032ba777a0","id":"t1gory2fsb4","title":"Definir horarios Supervisores.","desc":"Definir rotacional de supervisores mes de agosto.","resp":"Marco","due":"46232","prio":"baja","meet":"Seguimiento de tareas","meetdate":"","status":"proceso","created_at":"","updated_at":"","updated_by":"JFS","sync_status":"","deleted":"no"},{"@odata.etag":"","ItemInternalId":"0c6b2da7-136b-4d08-9f2e-14a0d770582c","id":"tg54vc76xmo","title":"Cierre herramienta ICU.","desc":"cierre conciliación herramienta DUAS ICU.","resp":"Marco","due":"46220","prio":"alta","meet":"Seguimiento de tareas","meetdate":"46217","status":"proceso","created_at":"","updated_at":"","updated_by":"JFS","sync_status":"","deleted":"no"},{"@odata.etag":"","ItemInternalId":"d41287db-5d33-41be-8214-cdb1f59d2ccf","id":"ttfnpmr0ziu","title":"Contratación digitador.","desc":"Contratación de nuevo personal","resp":"Marco","due":"46220","prio":"alta","meet":"Seguimiento de tareas","meetdate":"","status":"proceso","created_at":"","updated_at":"","updated_by":"JFS","sync_status":"","deleted":"no"},{"@odata.etag":"","ItemInternalId":"4dabf816-e5d2-46a2-9824-85eb3244c415","id":"tjkm0p3i38w","title":"Re implementación de muelles empaque.","desc":"Diseñar, marcar e implementar muelles de empaque.","resp":"Wallace","due":"46234","prio":"media","meet":"Seguimiento de tareas","meetdate":"","status":"proceso","created_at":"","updated_at":"","updated_by":"JFS","sync_status":"","deleted":"no"},{"@odata.etag":"","ItemInternalId":"185ccbb6-a183-4a8b-9efd-79216da4fd5e","id":"tfuixmd4qoc","title":"Capacitación profunda en WO Resineros.","desc":"Capacitación profunda a resineros en actividades de WO.","resp":"Wallace","due":"46232","prio":"media","meet":"Seguimiento de tareas","meetdate":"","status":"proceso","created_at":"","updated_at":"","updated_by":"JFS","sync_status":"","deleted":"no"},{"@odata.etag":"","ItemInternalId":"0193a173-b555-4202-803d-d90f1d0f9878","id":"txw362uzm4c","title":"Cierres WO.","desc":"Diseñar proceso para cierres ágiles de WO.","resp":"Marco","due":"46225","prio":"alta","meet":"Seguimiento de tareas","meetdate":"","status":"pendiente","created_at":"","updated_at":"","updated_by":"JFS","sync_status":"","deleted":"no"},{"@odata.etag":"","ItemInternalId":"9a488281-3e29-4fc4-b1f2-9217c4c19c1c","id":"th7f7og31uo","title":"Cambio en horario de molineros","desc":"Re acomodar los turnos de los molineros para dar soporte a ensamble automatizado.","resp":"Wallace","due":"46220","prio":"alta","meet":"Seguimiento de tareas","meetdate":"","status":"proceso","created_at":"","updated_at":"","updated_by":"JFS","sync_status":"","deleted":"no"}]