[{"@odata.etag":"","ItemInternalId":"46afbe51-76e4-41a7-9ace-959611ef7a54","id":"txw362uzm4c","title":"Cierres WO","desc":"Diseñar proceso para cierres ágiles de WO.","resp":"Marco","due":"46225","prio":"alta","meet":"Seguimiento de tareas","meetdate":"","status":"pendiente","created_at":"","updated_at":"","updated_by":"JFS","sync_status":"","deleted":"si"},{"@odata.etag":"","ItemInternalId":"6cb7bdff-d3e4-422f-b736-a26b551afac2","id":"tt4t243g56x","title":"Capacitación nuevo ingreso Digitador.","desc":"Capacitar y acompañar a nuevo ingreso digitador de almacén.","resp":"Eva","due":"46241","prio":"alta","meet":"Seguimiento de tareas","meetdate":"","status":"pendiente","created_at":"","updated_at":"","updated_by":"JFS","sync_status":"","deleted":"no"},{"@odata.etag":"","ItemInternalId":"4cf50b56-425e-4853-abf1-900de5bca634","id":"t0ytzl4qeei","title":"Capacitación operador Almacén.","desc":"Capacitar al nuevo operador de almacén (Edilson)","resp":"Erick","due":"46237","prio":"alta","meet":"Seguimiento de tareas","meetdate":"","status":"pendiente","created_at":"","updated_at":"","updated_by":"JFS","sync_status":"","deleted":"no"},{"@odata.etag":"","ItemInternalId":"818a7d4e-cf92-410a-a8e2-765bb9cd8ace","id":"t2ia39379rz","title":"Implementación 6S Almacén.","desc":"Capacitar e implementar la metodología de 6S en almacén.","resp":"Eva","due":"46249","prio":"baja","meet":"Administración diaria","meetdate":"46234","status":"pendiente","created_at":"","updated_at":"","updated_by":"JFS","sync_status":"","deleted":"no"},{"@odata.etag":"","ItemInternalId":"ba65d1d9-99b5-4899-91a2-778e4f6634e2","id":"tlm7ebzakdc","title":"Implementación 6S Almacén.","desc":"Capacitar e implementar la metodología de 6S en Almacén","resp":"Erick","due":"46234","prio":"baja","meet":"Administración diaria","meetdate":"46249","status":"pendiente","created_at":"","updated_at":"","updated_by":"JFS","sync_status":"","deleted":"si"},{"@odata.etag":"","ItemInternalId":"87846c62-2052-43f6-a3fd-ca8fe175a219","id":"tlm7ebzakdc","title":"Implementación 6S Almacén.","desc":"Capacitar e implementar la metodología de 6S en Almacén","resp":"Erick","due":"46219","prio":"baja","meet":"Administración diaria","meetdate":"46249","status":"pendiente","created_at":"","updated_at":"","updated_by":"JFS","sync_status":"","deleted":"no"},{"@odata.etag":"","ItemInternalId":"dd4fa9f1-1fc2-4792-81c6-ec0393afc32e","id":"t0iqnghmk9t","title":"Implementación 6S Almacén.","desc":"Capacitar e implementar la metodología de 6 S en almacén.","resp":"Wallace","due":"46234","prio":"baja","meet":"Administración diaria","meetdate":"46219","status":"pendiente","created_at":"","updated_at":"","updated_by":"JFS","sync_status":"","deleted":"no"},{"@odata.etag":"","ItemInternalId":"b23df57d-5108-4eb8-8aee-77bbc8bb2ac7","id":"t1gory2fsb4","title":"Definir horarios Supervisores.","desc":"Definir rotacional de supervisores mes de agosto.","resp":"Marco","due":"46232","prio":"baja","meet":"Seguimiento de tareas","meetdate":"","status":"proceso","created_at":"","updated_at":"","updated_by":"JFS","sync_status":"","deleted":"no"},{"@odata.etag":"","ItemInternalId":"5c57c19e-e532-42ee-9298-3396cbf580e9","id":"tg54vc76xmo","title":"Cierre herramienta ICU.","desc":"cierre conciliación herramienta DUAS ICU.","resp":"Marco","due":"46220","prio":"alta","meet":"Seguimiento de tareas","meetdate":"46217","status":"proceso","created_at":"","updated_at":"","updated_by":"JFS","sync_status":"","deleted":"no"},{"@odata.etag":"","ItemInternalId":"c9dfe456-68fc-4c75-a335-da7f2999b9ea","id":"ttfnpmr0ziu","title":"Contratación digitador.","desc":"Contratación de nuevo personal","resp":"Marco","due":"46220","prio":"alta","meet":"Seguimiento de tareas","meetdate":"","status":"proceso","created_at":"","updated_at":"","updated_by":"JFS","sync_status":"","deleted":"no"},{"@odata.etag":"","ItemInternalId":"4a4a8937-5a29-403c-8d2a-5c0c8b5780a0","id":"tjkm0p3i38w","title":"Re implementación de muelles empaque.","desc":"Diseñar, marcar e implementar muelles de empaque.","resp":"Wallace","due":"46234","prio":"media","meet":"Seguimiento de tareas","meetdate":"","status":"proceso","created_at":"","updated_at":"","updated_by":"JFS","sync_status":"","deleted":"no"},{"@odata.etag":"","ItemInternalId":"1e264d95-ed27-477e-acd3-270215cf987e","id":"tfuixmd4qoc","title":"Capacitación profunda en WO Resineros.","desc":"Capacitación profunda a resineros en actividades de WO.","resp":"Wallace","due":"46232","prio":"media","meet":"Seguimiento de tareas","meetdate":"","status":"proceso","created_at":"","updated_at":"","updated_by":"JFS","sync_status":"","deleted":"no"},{"@odata.etag":"","ItemInternalId":"1a1a78e2-83fb-4ece-9f42-8c64a764d74a","id":"txw362uzm4c","title":"Cierres WO.","desc":"Diseñar proceso para cierres ágiles de WO.","resp":"Marco","due":"46225","prio":"alta","meet":"Seguimiento de tareas","meetdate":"","status":"pendiente","created_at":"","updated_at":"","updated_by":"JFS","sync_status":"","deleted":"no"},{"@odata.etag":"","ItemInternalId":"091aab50-9629-47ab-bc66-0b240c969416","id":"th7f7og31uo","title":"Cambio en horario de molineros","desc":"Re acomodar los turnos de los molineros para dar soporte a ensamble automatizado.","resp":"Wallace","due":"46220","prio":"alta","meet":"Seguimiento de tareas","meetdate":"","status":"finalizada","created_at":"","updated_at":"","updated_by":"JFS","sync_status":"","deleted":"no"}]