[{"@odata.etag":"","ItemInternalId":"bec5152f-4365-4521-b1fb-0e413ed06262","id":"txw362uzm4c","title":"Cierres WO","desc":"Diseñar proceso para cierres ágiles de WO.","resp":"Marco","due":"46225","prio":"alta","meet":"Seguimiento de tareas","meetdate":"","status":"pendiente","created_at":"","updated_at":"","updated_by":"JFS","sync_status":"","deleted":"si","Comentario":""},{"@odata.etag":"","ItemInternalId":"c89d6f0d-5d82-46f8-a4d5-10aaefbbb573","id":"tt4t243g56x","title":"Capacitación nuevo ingreso Digitador.","desc":"Capacitar y acompañar a nuevo ingreso digitador de almacén.","resp":"Eva","due":"46241","prio":"alta","meet":"Seguimiento de tareas","meetdate":"","status":"pendiente","created_at":"","updated_at":"","updated_by":"JFS","sync_status":"","deleted":"no","Comentario":""},{"@odata.etag":"","ItemInternalId":"c9e51978-7cd3-4b10-832d-589b29f70bbf","id":"t0ytzl4qeei","title":"Capacitación operador Almacén.","desc":"Capacitar al nuevo operador de almacén (Edilson)","resp":"Erick","due":"46237","prio":"alta","meet":"Seguimiento de tareas","meetdate":"","status":"pendiente","created_at":"","updated_at":"","updated_by":"JFS","sync_status":"","deleted":"no","Comentario":""},{"@odata.etag":"","ItemInternalId":"8ec873bc-0af3-427a-a2fa-136d92a89d02","id":"t2ia39379rz","title":"Implementación 6S Almacén.","desc":"Capacitar e implementar la metodología de 6S en almacén.","resp":"Eva","due":"46249","prio":"baja","meet":"Administración diaria","meetdate":"46234","status":"pendiente","created_at":"","updated_at":"","updated_by":"JFS","sync_status":"","deleted":"no","Comentario":""},{"@odata.etag":"","ItemInternalId":"59f880de-431b-4d16-b0ff-f2a0920c09bf","id":"tlm7ebzakdc","title":"Implementación 6S Almacén.","desc":"Capacitar e implementar la metodología de 6S en Almacén","resp":"Erick","due":"46234","prio":"baja","meet":"Administración diaria","meetdate":"46249","status":"pendiente","created_at":"","updated_at":"","updated_by":"JFS","sync_status":"","deleted":"si","Comentario":""},{"@odata.etag":"","ItemInternalId":"ec050497-46be-461a-8b15-25e644ccf82a","id":"tlm7ebzakdc","title":"Implementación 6S Almacén.","desc":"Capacitar e implementar la metodología de 6S en Almacén","resp":"Erick","due":"46219","prio":"baja","meet":"Administración diaria","meetdate":"46249","status":"pendiente","created_at":"","updated_at":"","updated_by":"JFS","sync_status":"","deleted":"no","Comentario":""},{"@odata.etag":"","ItemInternalId":"d30d48f6-83a9-496a-b213-4e71eba92a2e","id":"t0iqnghmk9t","title":"Implementación 6S Almacén.","desc":"Capacitar e implementar la metodología de 6 S en almacén.","resp":"Wallace","due":"46234","prio":"baja","meet":"Administración diaria","meetdate":"46219","status":"pendiente","created_at":"","updated_at":"","updated_by":"JFS","sync_status":"","deleted":"no","Comentario":""},{"@odata.etag":"","ItemInternalId":"b528ad24-dec5-4dff-8687-e5d3c6194fcc","id":"t1gory2fsb4","title":"Definir horarios Supervisores.","desc":"Definir rotacional de supervisores mes de agosto.","resp":"Marco","due":"46232","prio":"baja","meet":"Seguimiento de tareas","meetdate":"","status":"proceso","created_at":"","updated_at":"","updated_by":"JFS","sync_status":"","deleted":"no","Comentario":""},{"@odata.etag":"","ItemInternalId":"4015f29c-d02f-449f-a8c6-06e1b6b5217a","id":"tg54vc76xmo","title":"Cierre herramienta ICU.","desc":"cierre conciliación herramienta DUAS ICU.","resp":"Marco","due":"46220","prio":"alta","meet":"Seguimiento de tareas","meetdate":"46217","status":"proceso","created_at":"","updated_at":"","updated_by":"JFS","sync_status":"","deleted":"no","Comentario":""},{"@odata.etag":"","ItemInternalId":"605542d6-e0bf-4e96-9fc1-5e9e7f489ccb","id":"ttfnpmr0ziu","title":"Contratación digitador.","desc":"Contratación de nuevo personal","resp":"Marco","due":"46220","prio":"alta","meet":"Seguimiento de tareas","meetdate":"","status":"proceso","created_at":"","updated_at":"","updated_by":"JFS","sync_status":"","deleted":"no","Comentario":""},{"@odata.etag":"","ItemInternalId":"b7067c8c-e474-4fdd-b3a8-0bccd24a05b5","id":"tjkm0p3i38w","title":"Re implementación de muelles empaque.","desc":"Diseñar, marcar e implementar muelles de empaque.","resp":"Wallace","due":"46234","prio":"media","meet":"Seguimiento de tareas","meetdate":"","status":"proceso","created_at":"","updated_at":"","updated_by":"JFS","sync_status":"","deleted":"no","Comentario":""},{"@odata.etag":"","ItemInternalId":"8f0ba455-0153-47b0-bdf2-3569a0824b77","id":"tfuixmd4qoc","title":"Capacitación profunda en WO Resineros.","desc":"Capacitación profunda a resineros en actividades de WO.","resp":"Wallace","due":"46232","prio":"media","meet":"Seguimiento de tareas","meetdate":"","status":"proceso","created_at":"","updated_at":"","updated_by":"JFS","sync_status":"","deleted":"no","Comentario":""},{"@odata.etag":"","ItemInternalId":"3779b360-51f2-47c1-8e02-e158916cc57a","id":"txw362uzm4c","title":"Cierres WO.","desc":"Diseñar proceso para cierres ágiles de WO.","resp":"Marco","due":"46225","prio":"alta","meet":"Seguimiento de tareas","meetdate":"","status":"pendiente","created_at":"","updated_at":"","updated_by":"JFS","sync_status":"","deleted":"no","Comentario":""},{"@odata.etag":"","ItemInternalId":"c10c87bb-226a-444e-9f2c-9cba886a5bf4","id":"th7f7og31uo","title":"Cambio en horario de molineros","desc":"Re acomodar los turnos de los molineros para dar soporte a ensamble automatizado.","resp":"Wallace","due":"46220","prio":"alta","meet":"Seguimiento de tareas","meetdate":"","status":"finalizada","created_at":"","updated_at":"","updated_by":"Jose","sync_status":"","deleted":"no","Comentario":""},{"@odata.etag":"","ItemInternalId":"d85a63d1-263e-4512-91e6-9ea6fc622776","id":"tuz5fxhpzqp","title":"Prueba Alex","desc":"Test","resp":"Alexander","due":"46225","prio":"alta","meet":"Reunión de producción","meetdate":"46225","status":"proceso","created_at":"","updated_at":"","updated_by":"ALM","sync_status":"","deleted":"si","Comentario":"Prueba para validación de tareas"},{"@odata.etag":"","ItemInternalId":"092f811a-f430-4b29-8780-8cd76092c929","id":"tuz5fxhpzqp","title":"Prueba Alex","desc":"Test","resp":"Alexander","due":"46225","prio":"alta","meet":"Reunión de producción","meetdate":"46225","status":"proceso","created_at":"","updated_at":"","updated_by":"Jose","sync_status":"","deleted":"si","Comentario":"Prueba para validación de tareas"},{"@odata.etag":"","ItemInternalId":"a313aa95-75ad-45a6-8bda-05bc80d7e011","id":"toee8ocyk8l","title":"Cotizar bolsa para el 82026 de Moog","desc":"Cotizar el incremento de la bolsa 9 al hacer el cambio por la anterior.","resp":"Jose","due":"46230","prio":"alta","meet":"Reunión con cliente","meetdate":"","status":"pendiente","created_at":"","updated_at":"","updated_by":"JFS","sync_status":"","deleted":"no","Comentario":"Revisar con Diego el cambio."}]