[{"@odata.etag":"","ItemInternalId":"2473cf03-f47c-4b00-b2f1-154518581466","id":"txw362uzm4c","title":"Cierres WO","desc":"Diseñar proceso para cierres ágiles de WO.","resp":"Marco","due":"46225","prio":"alta","meet":"Seguimiento de tareas","meetdate":"","status":"pendiente","created_at":"","updated_at":"","updated_by":"JFS","sync_status":"","deleted":"si","Comentario":""},{"@odata.etag":"","ItemInternalId":"d8b8b131-86cd-4472-897e-318ecffd025a","id":"tt4t243g56x","title":"Capacitación nuevo ingreso Digitador.","desc":"Capacitar y acompañar a nuevo ingreso digitador de almacén.","resp":"Eva","due":"46241","prio":"alta","meet":"Seguimiento de tareas","meetdate":"","status":"pendiente","created_at":"","updated_at":"","updated_by":"JFS","sync_status":"","deleted":"no","Comentario":""},{"@odata.etag":"","ItemInternalId":"c88c9919-cda8-4b26-bbd2-ef4b97ef40b7","id":"t0ytzl4qeei","title":"Capacitación operador Almacén.","desc":"Capacitar al nuevo operador de almacén (Edilson)","resp":"Erick","due":"46237","prio":"alta","meet":"Seguimiento de tareas","meetdate":"","status":"pendiente","created_at":"","updated_at":"","updated_by":"JFS","sync_status":"","deleted":"no","Comentario":""},{"@odata.etag":"","ItemInternalId":"f993d183-8567-450b-8fea-ac3403b97405","id":"t2ia39379rz","title":"Implementación 6S Almacén.","desc":"Capacitar e implementar la metodología de 6S en almacén.","resp":"Eva","due":"46249","prio":"baja","meet":"Administración diaria","meetdate":"46234","status":"pendiente","created_at":"","updated_at":"","updated_by":"JFS","sync_status":"","deleted":"no","Comentario":""},{"@odata.etag":"","ItemInternalId":"29b0c677-99bf-4118-a8ae-a0f0343b2c1e","id":"tlm7ebzakdc","title":"Implementación 6S Almacén.","desc":"Capacitar e implementar la metodología de 6S en Almacén","resp":"Erick","due":"46234","prio":"baja","meet":"Administración diaria","meetdate":"46249","status":"pendiente","created_at":"","updated_at":"","updated_by":"JFS","sync_status":"","deleted":"si","Comentario":""},{"@odata.etag":"","ItemInternalId":"9226d1fc-9e2a-4ecc-856a-39495aaee390","id":"tlm7ebzakdc","title":"Implementación 6S Almacén.","desc":"Capacitar e implementar la metodología de 6S en Almacén","resp":"Erick","due":"46219","prio":"baja","meet":"Administración diaria","meetdate":"46249","status":"pendiente","created_at":"","updated_at":"","updated_by":"JFS","sync_status":"","deleted":"no","Comentario":""},{"@odata.etag":"","ItemInternalId":"90fbb99c-9ab8-4f8f-a9f7-222f0ed6b226","id":"t0iqnghmk9t","title":"Implementación 6S Almacén.","desc":"Capacitar e implementar la metodología de 6 S en almacén.","resp":"Wallace","due":"46234","prio":"baja","meet":"Administración diaria","meetdate":"46219","status":"pendiente","created_at":"","updated_at":"","updated_by":"JFS","sync_status":"","deleted":"no","Comentario":""},{"@odata.etag":"","ItemInternalId":"9dc7da8e-a5c9-4ee5-8af8-b685d3131ca3","id":"t1gory2fsb4","title":"Definir horarios Supervisores.","desc":"Definir rotacional de supervisores mes de agosto.","resp":"Marco","due":"46232","prio":"baja","meet":"Seguimiento de tareas","meetdate":"","status":"proceso","created_at":"","updated_at":"","updated_by":"JFS","sync_status":"","deleted":"no","Comentario":""},{"@odata.etag":"","ItemInternalId":"cb8fc8e3-a5d8-46e7-85e8-0b0b9dc5df9f","id":"tg54vc76xmo","title":"Cierre herramienta ICU.","desc":"cierre conciliación herramienta DUAS ICU.","resp":"Marco","due":"46220","prio":"alta","meet":"Seguimiento de tareas","meetdate":"46217","status":"proceso","created_at":"","updated_at":"","updated_by":"JFS","sync_status":"","deleted":"no","Comentario":""},{"@odata.etag":"","ItemInternalId":"ae7dbc2b-91f7-46cb-9556-9ad1bb4ec3f7","id":"ttfnpmr0ziu","title":"Contratación digitador.","desc":"Contratación de nuevo personal","resp":"Marco","due":"46220","prio":"alta","meet":"Seguimiento de tareas","meetdate":"","status":"proceso","created_at":"","updated_at":"","updated_by":"JFS","sync_status":"","deleted":"no","Comentario":""},{"@odata.etag":"","ItemInternalId":"2124a03d-b0b8-4e4a-ae5c-d2d33c619277","id":"tjkm0p3i38w","title":"Re implementación de muelles empaque.","desc":"Diseñar, marcar e implementar muelles de empaque.","resp":"Wallace","due":"46234","prio":"media","meet":"Seguimiento de tareas","meetdate":"","status":"proceso","created_at":"","updated_at":"","updated_by":"JFS","sync_status":"","deleted":"no","Comentario":""},{"@odata.etag":"","ItemInternalId":"20734fc8-db48-4033-a875-d79abb25c829","id":"tfuixmd4qoc","title":"Capacitación profunda en WO Resineros.","desc":"Capacitación profunda a resineros en actividades de WO.","resp":"Wallace","due":"46232","prio":"media","meet":"Seguimiento de tareas","meetdate":"","status":"proceso","created_at":"","updated_at":"","updated_by":"JFS","sync_status":"","deleted":"no","Comentario":""},{"@odata.etag":"","ItemInternalId":"e37478a1-0126-4370-bc88-fdea75817fc9","id":"txw362uzm4c","title":"Cierres WO.","desc":"Diseñar proceso para cierres ágiles de WO.","resp":"Marco","due":"46225","prio":"alta","meet":"Seguimiento de tareas","meetdate":"","status":"pendiente","created_at":"","updated_at":"","updated_by":"JFS","sync_status":"","deleted":"no","Comentario":""},{"@odata.etag":"","ItemInternalId":"3daf7c11-eec3-401b-8e86-69841aad7a7f","id":"th7f7og31uo","title":"Cambio en horario de molineros","desc":"Re acomodar los turnos de los molineros para dar soporte a ensamble automatizado.","resp":"Wallace","due":"46220","prio":"alta","meet":"Seguimiento de tareas","meetdate":"","status":"finalizada","created_at":"","updated_at":"","updated_by":"Jose","sync_status":"","deleted":"no","Comentario":""},{"@odata.etag":"","ItemInternalId":"9ea2d019-1729-4e82-acae-f095b48577f9","id":"tuz5fxhpzqp","title":"Prueba Alex","desc":"Test","resp":"Alexander","due":"46225","prio":"alta","meet":"Reunión de producción","meetdate":"46225","status":"proceso","created_at":"","updated_at":"","updated_by":"Jose","sync_status":"","deleted":"no","Comentario":"Prueba para validación de tareas"},{"@odata.etag":"","ItemInternalId":"ad4bb883-fc59-4f5f-8597-78407b680961","id":"tuz5fxhpzqp","title":"Prueba Alex","desc":"Test","resp":"Alexander","due":"46225","prio":"alta","meet":"Reunión de producción","meetdate":"46225","status":"proceso","created_at":"","updated_at":"","updated_by":"Jose","sync_status":"","deleted":"si","Comentario":"Prueba para validación de tareas"}]